odoo10_addon_l10n_es_crm_lead_trade_name-10.0.1.0.0-py2.7-nspkg.pth
odoo/addons/l10n_es_crm_lead_trade_name/README.rst
odoo/addons/l10n_es_crm_lead_trade_name/__init__.py
odoo/addons/l10n_es_crm_lead_trade_name/__manifest__.py
odoo/addons/l10n_es_crm_lead_trade_name/i18n/bg.po
odoo/addons/l10n_es_crm_lead_trade_name/i18n/ca.po
odoo/addons/l10n_es_crm_lead_trade_name/i18n/es.po
odoo/addons/l10n_es_crm_lead_trade_name/i18n/eu.po
odoo/addons/l10n_es_crm_lead_trade_name/i18n/fr.po
odoo/addons/l10n_es_crm_lead_trade_name/i18n/gl.po
odoo/addons/l10n_es_crm_lead_trade_name/i18n/hr.po
odoo/addons/l10n_es_crm_lead_trade_name/i18n/l10n_es_crm_lead_trade_name.pot
odoo/addons/l10n_es_crm_lead_trade_name/i18n/pt_BR.po
odoo/addons/l10n_es_crm_lead_trade_name/models/__init__.py
odoo/addons/l10n_es_crm_lead_trade_name/models/crm_lead.py
odoo/addons/l10n_es_crm_lead_trade_name/static/description/icon.png
odoo/addons/l10n_es_crm_lead_trade_name/tests/__init__.py
odoo/addons/l10n_es_crm_lead_trade_name/tests/test_lead.py
odoo/addons/l10n_es_crm_lead_trade_name/views/crm_lead.xml
odoo10_addon_l10n_es_crm_lead_trade_name-10.0.1.0.0.dist-info/DESCRIPTION.rst
odoo10_addon_l10n_es_crm_lead_trade_name-10.0.1.0.0.dist-info/METADATA
odoo10_addon_l10n_es_crm_lead_trade_name-10.0.1.0.0.dist-info/RECORD
odoo10_addon_l10n_es_crm_lead_trade_name-10.0.1.0.0.dist-info/WHEEL
odoo10_addon_l10n_es_crm_lead_trade_name-10.0.1.0.0.dist-info/metadata.json
odoo10_addon_l10n_es_crm_lead_trade_name-10.0.1.0.0.dist-info/namespace_packages.txt
odoo10_addon_l10n_es_crm_lead_trade_name-10.0.1.0.0.dist-info/top_level.txt
