Metadata-Version: 2.0
Name: odoo10-addon-l10n-es-crm-lead-trade-name
Version: 10.0.1.0.0
Summary: Add trade name field to leads
Home-page: https://github.com/OCA/l10n-spain
Author: Antiun Ingeniería S.L.,QubiQ 2010,Odoo Community Association (OCA)
Author-email: support@odoo-community.org
License: AGPL-3
Platform: UNKNOWN
Classifier: Programming Language :: Python
Classifier: Framework :: Odoo
Classifier: License :: OSI Approved :: GNU Affero General Public License v3
Requires-Python: ~=2.7
Requires-Dist: odoo (<10.1dev,>=10.0)
Requires-Dist: odoo10-addon-l10n-es-partner
